rut_chile/__init__.py
rut_chile/rut_chile.py
rut_chile-2.0.1.dist-info/LICENSE
rut_chile-2.0.1.dist-info/METADATA
rut_chile-2.0.1.dist-info/WHEEL
rut_chile-2.0.1.dist-info/top_level.txt
rut_chile-2.0.1.dist-info/RECORD
