Metadata-Version: 2.1
Name: rut_chile
Version: 2.0.1
Summary: Package for validating Chilean RUT
Home-page: https://github.com/gevalenz/rut-chile
Author: Guillermo Valenzuela
Author-email: gevalenz@gmail.com
License: UNKNOWN
Keywords: RUT Chile
Platform: UNKNOWN
Classifier: Programming Language :: Python :: 3
Classifier: License :: OSI Approved :: MIT License
Classifier: Operating System :: OS Independent
License-File: LICENSE
